p3y3/__init__.py
p3y3-0.1.0.dist-info/METADATA
p3y3-0.1.0.dist-info/WHEEL
p3y3-0.1.0.dist-info/top_level.txt
p3y3-0.1.0.dist-info/RECORD
