Metadata-Version: 2.4
Name: p3y3
Version: 0.1.0
Summary: 3y3 encoding in python
Home-page: https://github.com/FAReTek1/p3y3
Author: faretek1
Author-email: 
License: MIT
Dynamic: author
Dynamic: description
Dynamic: description-content-type
Dynamic: home-page
Dynamic: license
Dynamic: summary
